libtextsearch_core.dylib
_textsearch.cpython-37m-darwin.so
fasttextsearch-0.12.dist-info/RECORD
fasttextsearch-0.12.dist-info/WHEEL
fasttextsearch-0.12.dist-info/top_level.txt
fasttextsearch-0.12.dist-info/METADATA
textsearch/suffix_array.py
textsearch/__init__.py
textsearch/datatypes.py
textsearch/utils.py
textsearch/levenshtein.py
textsearch/match.py
