Metadata-Version: 2.1
Name: fasttextsearch
Version: 0.12
Summary: Some fast-ish algorithms for batch text search in moderate-sized collections, intended for data cleanup.
Author-email: Next-gen Kaldi development team <wkang.pku@gmail.com>
Project-URL: Homepage, https://github.com/k2-fsa/text_search
Project-URL: Bug Tracker, https://github.com/k2-fsa/text_search/issues
Classifier: Programming Language :: Python :: 3
Classifier: License :: OSI Approved :: Apache Software License
Classifier: Operating System :: OS Independent
Requires-Python: >=3.7
Requires-Dist: numpy
Requires-Dist: regex
